opus_template/__init__.py
opus_template-0.1.0.dist-info/METADATA
opus_template-0.1.0.dist-info/WHEEL
opus_template-0.1.0.dist-info/entry_points.txt
opus_template-0.1.0.dist-info/RECORD
