Metadata-Version: 2.4
Name: opus-template
Version: 0.1.0
Summary: Add your description here
Requires-Python: >=3.13
Requires-Dist: plotly>=6.1.2
